track/__init__.py
track/autodetect.py
track/constants.py
track/convenience.py
track/error.py
track/log.py
track/logger.py
track/project.py
track/sync.py
track/trial.py
track/trials.py
track_ml-0.1.1.dist-info/METADATA
track_ml-0.1.1.dist-info/RECORD
track_ml-0.1.1.dist-info/WHEEL
track_ml-0.1.1.dist-info/top_level.txt
