Metadata-Version: 2.1
Name: track-ml
Version: 0.1.1
Summary: Experiment tracking module
Home-page: https://github.com/richardliaw/track
Author: RISE
License: MIT License
Platform: UNKNOWN
Requires-Dist: pandas (>=0.20.1)
Requires-Dist: absl-py (>=0.1.13)
Requires-Dist: pyyaml (>=3.12)
